aggregator/__init__.py
aggregator/aggregator.py
apis/__init__.py
apis/adzuna.py
apis/jooble.py
apis/linkedin.py
apis/remotive.py
apis/usajobs.py
config/__init__.py
config/config.py
mikelja-0.0.1.dist-info/LICENSE
mikelja-0.0.1.dist-info/METADATA
mikelja-0.0.1.dist-info/WHEEL
mikelja-0.0.1.dist-info/top_level.txt
mikelja-0.0.1.dist-info/RECORD
