Metadata-Version: 2.1
Name: mikelja
Version: 0.0.1
Summary: A Python library to aggregate job listings from various APIs.
Home-page: https://github.com/andy-birt/mikelja
Author: Andrew Birt
Author-email: Andrew Birt <andrew.birt@proton.me>
License: MIT License
Keywords: python,package,jobs,aggregator
Requires-Python: >=3.7
License-File: LICENSE
Requires-Dist: attrs>=24.3.0
Requires-Dist: beautifulsoup4>=4.12.3
Requires-Dist: certifi>=2024.8.30
Requires-Dist: cffi>=1.17.1
Requires-Dist: charset-normalizer>=3.4.0
Requires-Dist: h11>=0.14.0
Requires-Dist: idna>=3.10
Requires-Dist: outcome>=1.3.0.post0
Requires-Dist: pycparser>=2.22
Requires-Dist: PySocks>=1.7.1
Requires-Dist: python-dotenv>=1.0.1
Requires-Dist: requests>=2.32.3
Requires-Dist: selenium>=4.27.1
Requires-Dist: sniffio>=1.3.1
Requires-Dist: sortedcontainers>=2.4.0
Requires-Dist: soupsieve>=2.6
Requires-Dist: trio>=0.27.0
Requires-Dist: trio-websocket>=0.11.1
Requires-Dist: typing_extensions>=4.12.2
Requires-Dist: urllib3>=2.2.3
Requires-Dist: websocket-client>=1.8.0
Requires-Dist: wsproto>=1.2.0
